{
    "version": "0.4",
    "title": "Question Answer",
    "type": "page",
    "metadata": {
        "template_type": "single-page",
        "include_in_zip": "1",
        "elementor_pro_required": null,
        "wp_page_template": "elementor_header_footer"
    },
    "content": [
        {
            "id": "30db3645",
            "settings": {
                "content_width": {
                    "unit": "px",
                    "size": 1320,
                    "sizes": []
                },
                "structure": "20",
                "padding": {
                    "unit": "px",
                    "top": "100",
                    "right": "0",
                    "bottom": "100",
                    "left": "0",
                    "isLinked": false
                },
                "padding_tablet": {
                    "unit": "px",
                    "top": "50",
                    "right": "15",
                    "bottom": "50",
                    "left": "15",
                    "isLinked": false
                },
                "background_background": "classic",
                "background_image": {
                    "url": "https:\/\/gajean.com\/hanpot\/wp-content\/uploads\/sites\/27\/2023\/02\/male-photographer-back-view-1.jpg",
                    "id": 770,
                    "alt": "",
                    "source": "library"
                },
                "background_position": "center center",
                "background_size": "cover",
                "background_overlay_background": "gradient",
                "background_overlay_color_b_stop": {
                    "unit": "%",
                    "size": 70,
                    "sizes": []
                },
                "background_overlay_gradient_angle": {
                    "unit": "deg",
                    "size": 90,
                    "sizes": []
                },
                "background_overlay_opacity": {
                    "unit": "px",
                    "size": 1,
                    "sizes": []
                },
                "__globals__": {
                    "background_overlay_color": "globals\/colors?id=2e791f7",
                    "background_overlay_color_b": "globals\/colors?id=328789b"
                }
            },
            "elements": [
                {
                    "id": "75a30ca6",
                    "settings": {
                        "_column_size": 50,
                        "_inline_size": null,
                        "_inline_size_tablet": 100,
                        "padding": {
                            "unit": "px",
                            "top": "0",
                            "right": "30",
                            "bottom": "0",
                            "left": "0",
                            "isLinked": false
                        },
                        "padding_tablet": {
                            "unit": "px",
                            "top": "0",
                            "right": "0",
                            "bottom": "0",
                            "left": "0",
                            "isLinked": false
                        }
                    },
                    "elements": [],
                    "isInner": false,
                    "elType": "column"
                },
                {
                    "id": "4346f1f2",
                    "settings": {
                        "_column_size": 50,
                        "_inline_size": null,
                        "_inline_size_tablet": 100,
                        "padding": {
                            "unit": "px",
                            "top": "50",
                            "right": "50",
                            "bottom": "50",
                            "left": "50",
                            "isLinked": true
                        },
                        "padding_tablet": {
                            "unit": "px",
                            "top": "35",
                            "right": "35",
                            "bottom": "35",
                            "left": "35",
                            "isLinked": true
                        },
                        "background_background": "classic",
                        "background_color": "#FFFFFF",
                        "margin": {
                            "unit": "px",
                            "top": "0",
                            "right": "0",
                            "bottom": "0",
                            "left": "30",
                            "isLinked": false
                        },
                        "margin_tablet": {
                            "unit": "px",
                            "top": "0",
                            "right": "0",
                            "bottom": "0",
                            "left": "0",
                            "isLinked": false
                        },
                        "animation": "fadeInLeft"
                    },
                    "elements": [
                        {
                            "id": "150f82e1",
                            "settings": {
                                "view": "inline",
                                "icon_list": [
                                    {
                                        "text": "Homepage",
                                        "selected_icon": {
                                            "value": "",
                                            "library": ""
                                        },
                                        "_id": "f89bd0e",
                                        "link": {
                                            "url": "\/",
                                            "is_external": "",
                                            "nofollow": "",
                                            "custom_attributes": ""
                                        }
                                    },
                                    {
                                        "text": "Question Answer",
                                        "selected_icon": {
                                            "value": "remixicon ri-arrow-drop-right-line",
                                            "library": "remix-icons"
                                        },
                                        "_id": "891d352"
                                    }
                                ],
                                "icon_size": {
                                    "unit": "px",
                                    "size": 30,
                                    "sizes": []
                                },
                                "__globals__": {
                                    "icon_typography_typography": "globals\/typography?id=accent"
                                }
                            },
                            "elements": [],
                            "isInner": false,
                            "widgetType": "icon-list",
                            "elType": "widget"
                        },
                        {
                            "id": "c13d2b",
                            "settings": {
                                "ekit_heading_title": "{{Question}} Answer",
                                "ekit_heading_sub_title": "Time has changed",
                                "shadow_text_content": "bussiness",
                                "ekit_heading_show_seperator": "",
                                "ekit_heading_title_margin": {
                                    "unit": "px",
                                    "top": "0",
                                    "right": "0",
                                    "bottom": "0",
                                    "left": "0",
                                    "isLinked": false
                                },
                                "ekit_heading_title_typography_typography": "custom",
                                "ekit_heading_title_typography_font_family": "Poppins",
                                "ekit_heading_title_typography_font_size": {
                                    "unit": "px",
                                    "size": 45,
                                    "sizes": []
                                },
                                "ekit_heading_title_typography_font_size_tablet": {
                                    "unit": "px",
                                    "size": 35,
                                    "sizes": []
                                },
                                "ekit_heading_title_typography_font_size_mobile": {
                                    "unit": "px",
                                    "size": 30,
                                    "sizes": []
                                },
                                "ekit_heading_title_typography_font_weight": "700",
                                "ekit_heading_title_typography_text_transform": "uppercase",
                                "ekit_heading_title_typography_line_height": {
                                    "unit": "em",
                                    "size": 1.3,
                                    "sizes": []
                                },
                                "ekit_heading_title_typography_letter_spacing": {
                                    "unit": "px",
                                    "size": 0.7,
                                    "sizes": []
                                },
                                "ekit_heading_title_typography_word_spacing": {
                                    "unit": "em",
                                    "size": "",
                                    "sizes": []
                                },
                                "ekit_heading_focused_title_typography_typography": "custom",
                                "ekit_heading_focused_title_typography_font_family": "Poppins",
                                "ekit_heading_focused_title_typography_font_size": {
                                    "unit": "px",
                                    "size": 45,
                                    "sizes": []
                                },
                                "ekit_heading_focused_title_typography_font_size_tablet": {
                                    "unit": "px",
                                    "size": 35,
                                    "sizes": []
                                },
                                "ekit_heading_focused_title_typography_font_size_mobile": {
                                    "unit": "px",
                                    "size": 30,
                                    "sizes": []
                                },
                                "ekit_heading_focused_title_typography_font_weight": "700",
                                "ekit_heading_focused_title_typography_text_transform": "uppercase",
                                "ekit_heading_focused_title_typography_line_height": {
                                    "unit": "em",
                                    "size": 1.3,
                                    "sizes": []
                                },
                                "ekit_heading_focused_title_typography_letter_spacing": {
                                    "unit": "px",
                                    "size": 0.7,
                                    "sizes": []
                                },
                                "ekit_heading_focused_title_typography_word_spacing": {
                                    "unit": "em",
                                    "size": "",
                                    "sizes": []
                                },
                                "ekit_heading_use_focused_title_bg": "yes",
                                "ekit_heading_focused_title_secondary_bg_background": "classic",
                                "ekit_heading_focused_title_secondary_bg_color": "#121212",
                                "ekit_heading_use_title_text_fill": "",
                                "__globals__": {
                                    "ekit_heading_title_typography_typography": "globals\/typography?id=c397194",
                                    "ekit_heading_focused_title_typography_typography": "globals\/typography?id=c397194",
                                    "ekit_heading_focused_title_secondary_bg_color": "globals\/colors?id=4054cab",
                                    "ekit_heading_focused_title_color": "globals\/colors?id=primary",
                                    "ekit_heading_focused_title_color_hover": "globals\/colors?id=primary"
                                },
                                "ekit_heading_title_tag": "h3"
                            },
                            "elements": [],
                            "isInner": false,
                            "widgetType": "elementskit-heading",
                            "elType": "widget"
                        },
                        {
                            "id": "758862fb",
                            "settings": {
                                "width": {
                                    "unit": "px",
                                    "size": 350,
                                    "sizes": []
                                },
                                "width_tablet": {
                                    "unit": "px",
                                    "size": "",
                                    "sizes": []
                                },
                                "width_mobile": {
                                    "unit": "px",
                                    "size": "",
                                    "sizes": []
                                },
                                "look": "line_text",
                                "text": "Stay With Knowladge",
                                "weight": {
                                    "unit": "px",
                                    "size": 2,
                                    "sizes": []
                                },
                                "gap": {
                                    "unit": "px",
                                    "size": 5,
                                    "sizes": []
                                },
                                "text_align": "right",
                                "__globals__": {
                                    "typography_typography": "globals\/typography?id=accent",
                                    "text_color": "globals\/colors?id=text"
                                }
                            },
                            "elements": [],
                            "isInner": false,
                            "widgetType": "divider",
                            "elType": "widget"
                        }
                    ],
                    "isInner": false,
                    "elType": "column"
                }
            ],
            "isInner": false,
            "elType": "section"
        },
        {
            "id": "2dc73fad",
            "settings": {
                "content_width": {
                    "unit": "px",
                    "size": 1320,
                    "sizes": []
                },
                "structure": "20",
                "padding": {
                    "unit": "px",
                    "top": "100",
                    "right": "0",
                    "bottom": "100",
                    "left": "0",
                    "isLinked": false
                },
                "padding_tablet": {
                    "unit": "px",
                    "top": "50",
                    "right": "15",
                    "bottom": "50",
                    "left": "15",
                    "isLinked": false
                }
            },
            "elements": [
                {
                    "id": "fd1102a",
                    "settings": {
                        "_column_size": 50,
                        "_inline_size": 33,
                        "_inline_size_tablet": 100,
                        "padding": {
                            "unit": "px",
                            "top": "0",
                            "right": "30",
                            "bottom": "0",
                            "left": "0",
                            "isLinked": false
                        },
                        "padding_tablet": {
                            "unit": "px",
                            "top": "0",
                            "right": "0",
                            "bottom": "0",
                            "left": "0",
                            "isLinked": false
                        },
                        "content_position": "center"
                    },
                    "elements": [
                        {
                            "id": "3291c16",
                            "settings": {
                                "view": "inline",
                                "icon_list": [
                                    {
                                        "text": "Usually Asked",
                                        "selected_icon": {
                                            "value": "icon icon-photo-camera1",
                                            "library": "ekiticons"
                                        },
                                        "_id": "db73467"
                                    }
                                ],
                                "icon_size": {
                                    "unit": "px",
                                    "size": 25,
                                    "sizes": []
                                },
                                "__globals__": {
                                    "icon_typography_typography": "globals\/typography?id=3958d75",
                                    "text_color": "globals\/colors?id=c0dc0f8",
                                    "icon_color": "globals\/colors?id=primary"
                                },
                                "_animation": "fadeInUp"
                            },
                            "elements": [],
                            "isInner": false,
                            "widgetType": "icon-list",
                            "elType": "widget"
                        },
                        {
                            "id": "47e1e4b1",
                            "settings": {
                                "ekit_heading_title": "{{Frequently}} Asked Question",
                                "ekit_heading_sub_title": "Time has changed",
                                "shadow_text_content": "bussiness",
                                "ekit_heading_show_seperator": "",
                                "ekit_heading_title_margin": {
                                    "unit": "px",
                                    "top": "0",
                                    "right": "0",
                                    "bottom": "0",
                                    "left": "0",
                                    "isLinked": false
                                },
                                "ekit_heading_title_typography_typography": "custom",
                                "ekit_heading_title_typography_font_family": "Poppins",
                                "ekit_heading_title_typography_font_size": {
                                    "unit": "px",
                                    "size": 45,
                                    "sizes": []
                                },
                                "ekit_heading_title_typography_font_size_tablet": {
                                    "unit": "px",
                                    "size": 35,
                                    "sizes": []
                                },
                                "ekit_heading_title_typography_font_size_mobile": {
                                    "unit": "px",
                                    "size": 30,
                                    "sizes": []
                                },
                                "ekit_heading_title_typography_font_weight": "700",
                                "ekit_heading_title_typography_text_transform": "uppercase",
                                "ekit_heading_title_typography_line_height": {
                                    "unit": "em",
                                    "size": 1.3,
                                    "sizes": []
                                },
                                "ekit_heading_title_typography_letter_spacing": {
                                    "unit": "px",
                                    "size": 0.7,
                                    "sizes": []
                                },
                                "ekit_heading_title_typography_word_spacing": {
                                    "unit": "em",
                                    "size": "",
                                    "sizes": []
                                },
                                "ekit_heading_focused_title_typography_typography": "custom",
                                "ekit_heading_focused_title_typography_font_family": "Poppins",
                                "ekit_heading_focused_title_typography_font_size": {
                                    "unit": "px",
                                    "size": 45,
                                    "sizes": []
                                },
                                "ekit_heading_focused_title_typography_font_size_tablet": {
                                    "unit": "px",
                                    "size": 35,
                                    "sizes": []
                                },
                                "ekit_heading_focused_title_typography_font_size_mobile": {
                                    "unit": "px",
                                    "size": 30,
                                    "sizes": []
                                },
                                "ekit_heading_focused_title_typography_font_weight": "700",
                                "ekit_heading_focused_title_typography_text_transform": "uppercase",
                                "ekit_heading_focused_title_typography_line_height": {
                                    "unit": "em",
                                    "size": 1.3,
                                    "sizes": []
                                },
                                "ekit_heading_focused_title_typography_letter_spacing": {
                                    "unit": "px",
                                    "size": 0.7,
                                    "sizes": []
                                },
                                "ekit_heading_focused_title_typography_word_spacing": {
                                    "unit": "em",
                                    "size": "",
                                    "sizes": []
                                },
                                "ekit_heading_use_focused_title_bg": "yes",
                                "ekit_heading_focused_title_secondary_bg_background": "classic",
                                "ekit_heading_focused_title_secondary_bg_color": "#121212",
                                "ekit_heading_use_title_text_fill": "",
                                "__globals__": {
                                    "ekit_heading_title_typography_typography": "globals\/typography?id=c397194",
                                    "ekit_heading_focused_title_typography_typography": "globals\/typography?id=c397194",
                                    "ekit_heading_focused_title_secondary_bg_color": "globals\/colors?id=4054cab",
                                    "ekit_heading_focused_title_color": "globals\/colors?id=primary",
                                    "ekit_heading_focused_title_color_hover": "globals\/colors?id=primary"
                                },
                                "ekit_heading_title_tag": "h3",
                                "_animation": "fadeInUp",
                                "_animation_delay": 200
                            },
                            "elements": [],
                            "isInner": false,
                            "widgetType": "elementskit-heading",
                            "elType": "widget"
                        },
                        {
                            "id": "4fcf806f",
                            "settings": [],
                            "elements": [],
                            "isInner": false,
                            "widgetType": "text-editor",
                            "elType": "widget"
                        },
                        {
                            "id": "32bad1e6",
                            "settings": {
                                "title": "Is Not Answered ?",
                                "header_size": "h4"
                            },
                            "elements": [],
                            "isInner": false,
                            "widgetType": "heading",
                            "elType": "widget"
                        },
                        {
                            "id": "4e95a46a",
                            "settings": {
                                "text": "Talk With Me",
                                "selected_icon": {
                                    "value": "teenyicon ti-arrow-right",
                                    "library": "teeny-icons"
                                },
                                "icon_align": "right",
                                "icon_indent": {
                                    "unit": "px",
                                    "size": 10,
                                    "sizes": []
                                },
                                "hover_animation": "float",
                                "_margin": {
                                    "unit": "px",
                                    "top": "0",
                                    "right": "0",
                                    "bottom": "0",
                                    "left": "0",
                                    "isLinked": false
                                }
                            },
                            "elements": [],
                            "isInner": false,
                            "widgetType": "button",
                            "elType": "widget"
                        }
                    ],
                    "isInner": false,
                    "elType": "column"
                },
                {
                    "id": "19f1f263",
                    "settings": {
                        "_column_size": 50,
                        "_inline_size": 67,
                        "_inline_size_tablet": 100,
                        "padding": {
                            "unit": "px",
                            "top": "0",
                            "right": "0",
                            "bottom": "0",
                            "left": "30",
                            "isLinked": false
                        },
                        "padding_tablet": {
                            "unit": "px",
                            "top": "30",
                            "right": "0",
                            "bottom": "0",
                            "left": "0",
                            "isLinked": false
                        }
                    },
                    "elements": [
                        {
                            "id": "45983e63",
                            "settings": {
                                "structure": "20"
                            },
                            "elements": [
                                {
                                    "id": "7adce4bf",
                                    "settings": {
                                        "_column_size": 50,
                                        "_inline_size": null,
                                        "content_position_tablet": "center",
                                        "padding": {
                                            "unit": "px",
                                            "top": "0",
                                            "right": "30",
                                            "bottom": "0",
                                            "left": "0",
                                            "isLinked": false
                                        },
                                        "padding_tablet": {
                                            "unit": "px",
                                            "top": "0",
                                            "right": "15",
                                            "bottom": "0",
                                            "left": "0",
                                            "isLinked": false
                                        },
                                        "padding_mobile": {
                                            "unit": "px",
                                            "top": "0",
                                            "right": "0",
                                            "bottom": "0",
                                            "left": "0",
                                            "isLinked": false
                                        }
                                    },
                                    "elements": [
                                        {
                                            "id": "623c1b7b",
                                            "settings": {
                                                "youtube_url": "https:\/\/www.youtube.com\/watch?v=XHOmBV4js_E",
                                                "vimeo_url": "https:\/\/vimeo.com\/235215203",
                                                "dailymotion_url": "https:\/\/www.dailymotion.com\/video\/x6tqhqb",
                                                "show_image_overlay": "yes",
                                                "image_overlay": {
                                                    "url": "https:\/\/gajean.com\/hanpot\/wp-content\/uploads\/sites\/27\/2023\/02\/young-photographer-in-wintertime-1.jpg",
                                                    "id": 777,
                                                    "alt": "",
                                                    "source": "library"
                                                },
                                                "image_overlay_size": "custom",
                                                "image_overlay_custom_dimension": {
                                                    "width": "600",
                                                    "height": "800"
                                                },
                                                "lightbox": "yes"
                                            },
                                            "elements": [],
                                            "isInner": false,
                                            "widgetType": "video",
                                            "elType": "widget"
                                        }
                                    ],
                                    "isInner": true,
                                    "elType": "column"
                                },
                                {
                                    "id": "1479a74f",
                                    "settings": {
                                        "_column_size": 50,
                                        "_inline_size": null,
                                        "content_position": "center",
                                        "padding": {
                                            "unit": "px",
                                            "top": "0",
                                            "right": "0",
                                            "bottom": "0",
                                            "left": "30",
                                            "isLinked": false
                                        },
                                        "padding_tablet": {
                                            "unit": "px",
                                            "top": "0",
                                            "right": "0",
                                            "bottom": "0",
                                            "left": "15",
                                            "isLinked": false
                                        },
                                        "padding_mobile": {
                                            "unit": "px",
                                            "top": "30",
                                            "right": "0",
                                            "bottom": "0",
                                            "left": "0",
                                            "isLinked": false
                                        }
                                    },
                                    "elements": [
                                        {
                                            "id": "19210e6a",
                                            "settings": {
                                                "selected_icon": {
                                                    "value": "remixicon ri-question-mark",
                                                    "library": "remix-icons"
                                                },
                                                "view": "stacked",
                                                "shape": "square",
                                                "title_text": "Lets Get Answerd",
                                                "description_text": "Gresik United Nggepeng Village East Java",
                                                "position": "left",
                                                "title_size": "h4",
                                                "secondary_color": "#FFFFFF",
                                                "icon_space": {
                                                    "unit": "px",
                                                    "size": 25,
                                                    "sizes": []
                                                },
                                                "icon_size": {
                                                    "unit": "px",
                                                    "size": 30,
                                                    "sizes": []
                                                },
                                                "content_vertical_alignment": "middle",
                                                "title_bottom_space": {
                                                    "unit": "px",
                                                    "size": 5,
                                                    "sizes": []
                                                },
                                                "__globals__": {
                                                    "primary_color": "globals\/colors?id=primary"
                                                },
                                                "position_mobile": "left"
                                            },
                                            "elements": [],
                                            "isInner": false,
                                            "widgetType": "icon-box",
                                            "elType": "widget"
                                        },
                                        {
                                            "id": "132b4015",
                                            "settings": {
                                                "ekit_accordion_items": [
                                                    {
                                                        "acc_title": "How To Get Quotation ?",
                                                        "acc_content": "<p>Far far away, behind the word mountains, far from the countries Vokalia and Consonantia, there live the blind texts. Separated they live in\u00a0<\/p>",
                                                        "ekit_acc_is_active": "",
                                                        "_id": "0d73331"
                                                    },
                                                    {
                                                        "acc_title": "How Long Enqueue ?",
                                                        "_id": "6ea87b7"
                                                    },
                                                    {
                                                        "acc_title": "Personal Photographer ?",
                                                        "_id": "ef04211"
                                                    }
                                                ],
                                                "ekit_accordion_right_icon_actives": {
                                                    "value": "icon icon-up-arrow1",
                                                    "library": "ekiticons"
                                                },
                                                "ekit_accordion_background_background": "classic",
                                                "ekit_accordion_border_radious_curve_shape_open": {
                                                    "unit": "px",
                                                    "top": "0",
                                                    "right": "0",
                                                    "bottom": "0",
                                                    "left": "0",
                                                    "isLinked": false
                                                },
                                                "ekit_accordion_background_close_background": "classic",
                                                "ekit_accordion_title_padding": {
                                                    "unit": "px",
                                                    "top": "20",
                                                    "right": "20",
                                                    "bottom": "20",
                                                    "left": "20",
                                                    "isLinked": true
                                                },
                                                "ekit_accordion_content_padding": {
                                                    "unit": "px",
                                                    "top": "20",
                                                    "right": "20",
                                                    "bottom": "20",
                                                    "left": "20",
                                                    "isLinked": true
                                                },
                                                "ekit_accordion_icon_typography_close": {
                                                    "unit": "px",
                                                    "size": 15,
                                                    "sizes": []
                                                },
                                                "ekit_accordion_icon_typography": {
                                                    "unit": "px",
                                                    "size": 15,
                                                    "sizes": []
                                                },
                                                "__globals__": {
                                                    "ekit_accordion_title_typography_typography": "globals\/typography?id=4aceb21",
                                                    "ekit_accordion_background_color": "globals\/colors?id=4054cab",
                                                    "ekit_accordion_background_close_color": "globals\/colors?id=4054cab",
                                                    "ekit_accordion_title_color": "globals\/colors?id=primary",
                                                    "ekit_accordion_title_color_close": "globals\/colors?id=text",
                                                    "ekit_accordion_icon_color_close": "globals\/colors?id=text",
                                                    "ekit_accordion_icon_color": "globals\/colors?id=primary"
                                                }
                                            },
                                            "elements": [],
                                            "isInner": false,
                                            "widgetType": "elementskit-accordion",
                                            "elType": "widget"
                                        }
                                    ],
                                    "isInner": true,
                                    "elType": "column"
                                }
                            ],
                            "isInner": true,
                            "elType": "section"
                        }
                    ],
                    "isInner": false,
                    "elType": "column"
                }
            ],
            "isInner": false,
            "elType": "section"
        },
        {
            "id": "315ac2cf",
            "settings": {
                "content_width": {
                    "unit": "px",
                    "size": 1320,
                    "sizes": []
                },
                "padding": {
                    "unit": "px",
                    "top": "0",
                    "right": "0",
                    "bottom": "100",
                    "left": "0",
                    "isLinked": false
                },
                "padding_tablet": {
                    "unit": "px",
                    "top": "0",
                    "right": "15",
                    "bottom": "50",
                    "left": "15",
                    "isLinked": false
                },
                "gap": "no"
            },
            "elements": [
                {
                    "id": "1ba63e34",
                    "settings": {
                        "_column_size": 100,
                        "_inline_size": null
                    },
                    "elements": [
                        {
                            "id": "3b77fd79",
                            "settings": {
                                "content_width": {
                                    "unit": "px",
                                    "size": 720,
                                    "sizes": []
                                },
                                "gap": "no",
                                "margin": {
                                    "unit": "px",
                                    "top": "0",
                                    "right": 0,
                                    "bottom": "35",
                                    "left": 0,
                                    "isLinked": false
                                }
                            },
                            "elements": [
                                {
                                    "id": "280f8781",
                                    "settings": {
                                        "_column_size": 100,
                                        "_inline_size": null
                                    },
                                    "elements": [
                                        {
                                            "id": "2a96e29e",
                                            "settings": {
                                                "view": "inline",
                                                "icon_list": [
                                                    {
                                                        "text": "General Question",
                                                        "selected_icon": {
                                                            "value": "icon icon-photo-camera1",
                                                            "library": "ekiticons"
                                                        },
                                                        "_id": "db73467"
                                                    }
                                                ],
                                                "icon_size": {
                                                    "unit": "px",
                                                    "size": 25,
                                                    "sizes": []
                                                },
                                                "__globals__": {
                                                    "icon_typography_typography": "globals\/typography?id=3958d75",
                                                    "text_color": "globals\/colors?id=c0dc0f8",
                                                    "icon_color": "globals\/colors?id=primary"
                                                },
                                                "icon_align": "center",
                                                "_animation": "fadeInUp"
                                            },
                                            "elements": [],
                                            "isInner": false,
                                            "widgetType": "icon-list",
                                            "elType": "widget"
                                        },
                                        {
                                            "id": "2cbb5806",
                                            "settings": {
                                                "ekit_heading_title": "{{Find General}} Question Answer From Client",
                                                "ekit_heading_sub_title": "Time has changed",
                                                "shadow_text_content": "bussiness",
                                                "ekit_heading_show_seperator": "",
                                                "ekit_heading_title_margin": {
                                                    "unit": "px",
                                                    "top": "0",
                                                    "right": "0",
                                                    "bottom": "0",
                                                    "left": "0",
                                                    "isLinked": false
                                                },
                                                "ekit_heading_title_typography_typography": "custom",
                                                "ekit_heading_title_typography_font_family": "Poppins",
                                                "ekit_heading_title_typography_font_size": {
                                                    "unit": "px",
                                                    "size": 45,
                                                    "sizes": []
                                                },
                                                "ekit_heading_title_typography_font_size_tablet": {
                                                    "unit": "px",
                                                    "size": 35,
                                                    "sizes": []
                                                },
                                                "ekit_heading_title_typography_font_size_mobile": {
                                                    "unit": "px",
                                                    "size": 30,
                                                    "sizes": []
                                                },
                                                "ekit_heading_title_typography_font_weight": "700",
                                                "ekit_heading_title_typography_line_height": {
                                                    "unit": "em",
                                                    "size": 1.3,
                                                    "sizes": []
                                                },
                                                "ekit_heading_title_typography_word_spacing": {
                                                    "unit": "em",
                                                    "size": "",
                                                    "sizes": []
                                                },
                                                "ekit_heading_focused_title_color": "#121212",
                                                "ekit_heading_focused_title_color_hover": "#121212",
                                                "ekit_heading_focused_title_typography_typography": "custom",
                                                "ekit_heading_focused_title_typography_font_family": "Poppins",
                                                "ekit_heading_focused_title_typography_font_size": {
                                                    "unit": "px",
                                                    "size": 45,
                                                    "sizes": []
                                                },
                                                "ekit_heading_focused_title_typography_font_size_tablet": {
                                                    "unit": "px",
                                                    "size": 35,
                                                    "sizes": []
                                                },
                                                "ekit_heading_focused_title_typography_font_size_mobile": {
                                                    "unit": "px",
                                                    "size": 30,
                                                    "sizes": []
                                                },
                                                "ekit_heading_focused_title_typography_font_weight": "700",
                                                "ekit_heading_focused_title_typography_line_height": {
                                                    "unit": "em",
                                                    "size": 1.3,
                                                    "sizes": []
                                                },
                                                "ekit_heading_focused_title_typography_word_spacing": {
                                                    "unit": "em",
                                                    "size": "",
                                                    "sizes": []
                                                },
                                                "ekit_heading_use_focused_title_bg": "yes",
                                                "ekit_heading_focused_title_secondary_bg_background": "classic",
                                                "ekit_heading_use_title_text_fill": "",
                                                "__globals__": {
                                                    "ekit_heading_title_typography_typography": "globals\/typography?id=c397194",
                                                    "ekit_heading_focused_title_typography_typography": "globals\/typography?id=c397194",
                                                    "ekit_heading_focused_title_secondary_bg_color": "globals\/colors?id=4054cab",
                                                    "ekit_heading_focused_title_color": "globals\/colors?id=primary",
                                                    "ekit_heading_focused_title_color_hover": "globals\/colors?id=accent"
                                                },
                                                "ekit_heading_title_tag": "h3",
                                                "ekit_heading_title_align": "text_center",
                                                "_animation": "fadeInUp",
                                                "_animation_delay": 200
                                            },
                                            "elements": [],
                                            "isInner": false,
                                            "widgetType": "elementskit-heading",
                                            "elType": "widget"
                                        }
                                    ],
                                    "isInner": true,
                                    "elType": "column"
                                }
                            ],
                            "isInner": true,
                            "elType": "section"
                        },
                        {
                            "id": "78204248",
                            "settings": {
                                "gap": "custom",
                                "gap_columns_custom": {
                                    "unit": "px",
                                    "size": 15,
                                    "sizes": []
                                },
                                "structure": "20"
                            },
                            "elements": [
                                {
                                    "id": "51eba493",
                                    "settings": {
                                        "_column_size": 50,
                                        "_inline_size": null
                                    },
                                    "elements": [
                                        {
                                            "id": "59ffdca4",
                                            "settings": {
                                                "ekit_accordion_items": [
                                                    {
                                                        "acc_title": "How To Get Quotation ?",
                                                        "ekit_acc_is_active": "",
                                                        "_id": "0d73331"
                                                    },
                                                    {
                                                        "acc_title": "How Long Enqueue ?",
                                                        "_id": "6ea87b7"
                                                    },
                                                    {
                                                        "acc_title": "Personal Photographer ?",
                                                        "_id": "ef04211"
                                                    }
                                                ],
                                                "ekit_accordion_right_icon_actives": {
                                                    "value": "icon icon-up-arrow1",
                                                    "library": "ekiticons"
                                                },
                                                "ekit_accordion_background_background": "classic",
                                                "ekit_accordion_border_radious_curve_shape_open": {
                                                    "unit": "px",
                                                    "top": "0",
                                                    "right": "0",
                                                    "bottom": "0",
                                                    "left": "0",
                                                    "isLinked": false
                                                },
                                                "ekit_accordion_background_close_background": "classic",
                                                "ekit_accordion_title_padding": {
                                                    "unit": "px",
                                                    "top": "20",
                                                    "right": "20",
                                                    "bottom": "20",
                                                    "left": "20",
                                                    "isLinked": true
                                                },
                                                "ekit_accordion_content_padding": {
                                                    "unit": "px",
                                                    "top": "20",
                                                    "right": "20",
                                                    "bottom": "20",
                                                    "left": "20",
                                                    "isLinked": true
                                                },
                                                "ekit_accordion_icon_typography_close": {
                                                    "unit": "px",
                                                    "size": 15,
                                                    "sizes": []
                                                },
                                                "ekit_accordion_icon_typography": {
                                                    "unit": "px",
                                                    "size": 15,
                                                    "sizes": []
                                                },
                                                "__globals__": {
                                                    "ekit_accordion_title_typography_typography": "globals\/typography?id=4aceb21",
                                                    "ekit_accordion_background_color": "globals\/colors?id=4054cab",
                                                    "ekit_accordion_background_close_color": "globals\/colors?id=4054cab",
                                                    "ekit_accordion_title_color": "globals\/colors?id=primary",
                                                    "ekit_accordion_title_color_close": "globals\/colors?id=text",
                                                    "ekit_accordion_icon_color_close": "globals\/colors?id=text",
                                                    "ekit_accordion_icon_color": "globals\/colors?id=primary"
                                                }
                                            },
                                            "elements": [],
                                            "isInner": false,
                                            "widgetType": "elementskit-accordion",
                                            "elType": "widget"
                                        }
                                    ],
                                    "isInner": true,
                                    "elType": "column"
                                },
                                {
                                    "id": "2d7a4f27",
                                    "settings": {
                                        "_column_size": 50,
                                        "_inline_size": null
                                    },
                                    "elements": [
                                        {
                                            "id": "39e1b1ec",
                                            "settings": {
                                                "ekit_accordion_items": [
                                                    {
                                                        "acc_title": "How To Get Quotation ?",
                                                        "ekit_acc_is_active": "",
                                                        "_id": "0d73331"
                                                    },
                                                    {
                                                        "acc_title": "How Long Enqueue ?",
                                                        "_id": "6ea87b7"
                                                    },
                                                    {
                                                        "acc_title": "Personal Photographer ?",
                                                        "_id": "ef04211"
                                                    }
                                                ],
                                                "ekit_accordion_right_icon_actives": {
                                                    "value": "icon icon-up-arrow1",
                                                    "library": "ekiticons"
                                                },
                                                "ekit_accordion_background_background": "classic",
                                                "ekit_accordion_border_radious_curve_shape_open": {
                                                    "unit": "px",
                                                    "top": "0",
                                                    "right": "0",
                                                    "bottom": "0",
                                                    "left": "0",
                                                    "isLinked": false
                                                },
                                                "ekit_accordion_background_close_background": "classic",
                                                "ekit_accordion_title_padding": {
                                                    "unit": "px",
                                                    "top": "20",
                                                    "right": "20",
                                                    "bottom": "20",
                                                    "left": "20",
                                                    "isLinked": true
                                                },
                                                "ekit_accordion_content_padding": {
                                                    "unit": "px",
                                                    "top": "20",
                                                    "right": "20",
                                                    "bottom": "20",
                                                    "left": "20",
                                                    "isLinked": true
                                                },
                                                "ekit_accordion_icon_typography_close": {
                                                    "unit": "px",
                                                    "size": 15,
                                                    "sizes": []
                                                },
                                                "ekit_accordion_icon_typography": {
                                                    "unit": "px",
                                                    "size": 15,
                                                    "sizes": []
                                                },
                                                "__globals__": {
                                                    "ekit_accordion_title_typography_typography": "globals\/typography?id=4aceb21",
                                                    "ekit_accordion_background_color": "globals\/colors?id=4054cab",
                                                    "ekit_accordion_background_close_color": "globals\/colors?id=4054cab",
                                                    "ekit_accordion_title_color": "globals\/colors?id=primary",
                                                    "ekit_accordion_title_color_close": "globals\/colors?id=text",
                                                    "ekit_accordion_icon_color_close": "globals\/colors?id=text",
                                                    "ekit_accordion_icon_color": "globals\/colors?id=primary"
                                                }
                                            },
                                            "elements": [],
                                            "isInner": false,
                                            "widgetType": "elementskit-accordion",
                                            "elType": "widget"
                                        }
                                    ],
                                    "isInner": true,
                                    "elType": "column"
                                }
                            ],
                            "isInner": true,
                            "elType": "section"
                        }
                    ],
                    "isInner": false,
                    "elType": "column"
                }
            ],
            "isInner": false,
            "elType": "section"
        },
        {
            "id": "1fd2c51c",
            "settings": {
                "content_width": {
                    "unit": "px",
                    "size": 1320,
                    "sizes": []
                },
                "padding": {
                    "unit": "px",
                    "top": "0",
                    "right": "0",
                    "bottom": "100",
                    "left": "0",
                    "isLinked": false
                },
                "padding_tablet": {
                    "unit": "px",
                    "top": "0",
                    "right": "15",
                    "bottom": "50",
                    "left": "15",
                    "isLinked": false
                },
                "gap": "no"
            },
            "elements": [
                {
                    "id": "78bba58b",
                    "settings": {
                        "_column_size": 100,
                        "_inline_size": null
                    },
                    "elements": [
                        {
                            "id": "119cc162",
                            "settings": {
                                "content_width": {
                                    "unit": "px",
                                    "size": 720,
                                    "sizes": []
                                },
                                "gap": "no",
                                "margin": {
                                    "unit": "px",
                                    "top": "0",
                                    "right": 0,
                                    "bottom": "35",
                                    "left": 0,
                                    "isLinked": false
                                }
                            },
                            "elements": [
                                {
                                    "id": "7dfc3cfb",
                                    "settings": {
                                        "_column_size": 100,
                                        "_inline_size": null
                                    },
                                    "elements": [
                                        {
                                            "id": "55d80d61",
                                            "settings": {
                                                "view": "inline",
                                                "icon_list": [
                                                    {
                                                        "text": "Photography Resource",
                                                        "selected_icon": {
                                                            "value": "icon icon-photo-camera1",
                                                            "library": "ekiticons"
                                                        },
                                                        "_id": "db73467"
                                                    }
                                                ],
                                                "icon_size": {
                                                    "unit": "px",
                                                    "size": 25,
                                                    "sizes": []
                                                },
                                                "__globals__": {
                                                    "icon_typography_typography": "globals\/typography?id=3958d75",
                                                    "text_color": "globals\/colors?id=c0dc0f8",
                                                    "icon_color": "globals\/colors?id=primary"
                                                },
                                                "icon_align": "center",
                                                "_animation": "fadeInUp"
                                            },
                                            "elements": [],
                                            "isInner": false,
                                            "widgetType": "icon-list",
                                            "elType": "widget"
                                        },
                                        {
                                            "id": "6962b08d",
                                            "settings": {
                                                "ekit_heading_title": "{{Read My}} Personal Blog",
                                                "ekit_heading_sub_title": "Time has changed",
                                                "shadow_text_content": "bussiness",
                                                "ekit_heading_show_seperator": "",
                                                "ekit_heading_title_margin": {
                                                    "unit": "px",
                                                    "top": "0",
                                                    "right": "0",
                                                    "bottom": "0",
                                                    "left": "0",
                                                    "isLinked": false
                                                },
                                                "ekit_heading_title_typography_typography": "custom",
                                                "ekit_heading_title_typography_font_family": "Poppins",
                                                "ekit_heading_title_typography_font_size": {
                                                    "unit": "px",
                                                    "size": 45,
                                                    "sizes": []
                                                },
                                                "ekit_heading_title_typography_font_size_tablet": {
                                                    "unit": "px",
                                                    "size": 35,
                                                    "sizes": []
                                                },
                                                "ekit_heading_title_typography_font_size_mobile": {
                                                    "unit": "px",
                                                    "size": 30,
                                                    "sizes": []
                                                },
                                                "ekit_heading_title_typography_font_weight": "700",
                                                "ekit_heading_title_typography_line_height": {
                                                    "unit": "em",
                                                    "size": 1.3,
                                                    "sizes": []
                                                },
                                                "ekit_heading_title_typography_word_spacing": {
                                                    "unit": "em",
                                                    "size": "",
                                                    "sizes": []
                                                },
                                                "ekit_heading_focused_title_color": "#121212",
                                                "ekit_heading_focused_title_color_hover": "#121212",
                                                "ekit_heading_focused_title_typography_typography": "custom",
                                                "ekit_heading_focused_title_typography_font_family": "Poppins",
                                                "ekit_heading_focused_title_typography_font_size": {
                                                    "unit": "px",
                                                    "size": 45,
                                                    "sizes": []
                                                },
                                                "ekit_heading_focused_title_typography_font_size_tablet": {
                                                    "unit": "px",
                                                    "size": 35,
                                                    "sizes": []
                                                },
                                                "ekit_heading_focused_title_typography_font_size_mobile": {
                                                    "unit": "px",
                                                    "size": 30,
                                                    "sizes": []
                                                },
                                                "ekit_heading_focused_title_typography_font_weight": "700",
                                                "ekit_heading_focused_title_typography_line_height": {
                                                    "unit": "em",
                                                    "size": 1.3,
                                                    "sizes": []
                                                },
                                                "ekit_heading_focused_title_typography_word_spacing": {
                                                    "unit": "em",
                                                    "size": "",
                                                    "sizes": []
                                                },
                                                "ekit_heading_use_focused_title_bg": "yes",
                                                "ekit_heading_focused_title_secondary_bg_background": "classic",
                                                "ekit_heading_use_title_text_fill": "",
                                                "__globals__": {
                                                    "ekit_heading_title_typography_typography": "globals\/typography?id=c397194",
                                                    "ekit_heading_focused_title_typography_typography": "globals\/typography?id=c397194",
                                                    "ekit_heading_focused_title_secondary_bg_color": "globals\/colors?id=4054cab",
                                                    "ekit_heading_focused_title_color": "globals\/colors?id=primary",
                                                    "ekit_heading_focused_title_color_hover": "globals\/colors?id=accent"
                                                },
                                                "ekit_heading_title_tag": "h3",
                                                "ekit_heading_title_align": "text_center",
                                                "_animation": "fadeInUp",
                                                "_animation_delay": 200
                                            },
                                            "elements": [],
                                            "isInner": false,
                                            "widgetType": "elementskit-heading",
                                            "elType": "widget"
                                        }
                                    ],
                                    "isInner": true,
                                    "elType": "column"
                                }
                            ],
                            "isInner": true,
                            "elType": "section"
                        },
                        {
                            "id": "4820e2d7",
                            "settings": {
                                "ekit_blog_posts_layout_style": "elementskit-post-image-card",
                                "ekit_blog_posts_is_manual_selection": "recent",
                                "ekit_blog_posts_cats": [
                                    "4"
                                ],
                                "ekit_blog_posts_floating_date": "yes",
                                "ekit_blog_posts_floating_date_style": "style2",
                                "ekit_blog_posts_floating_category": "yes",
                                "ekit_blog_posts_btn_text": "Learn more ",
                                "ekit_blog_posts_background_background": "classic",
                                "ekit_blog_posts_background_color": "#F9F9F9",
                                "ekit_blog_posts_shadow_box_shadow_type": "yes",
                                "ekit_blog_posts_shadow_box_shadow": {
                                    "horizontal": 0,
                                    "vertical": 0,
                                    "blur": 10,
                                    "spread": 0,
                                    "color": "rgba(0, 0, 0, 0)"
                                },
                                "ekit_blog_posts_radius": {
                                    "unit": "px",
                                    "top": "0",
                                    "right": "0",
                                    "bottom": "0",
                                    "left": "0",
                                    "isLinked": false
                                },
                                "ekit_blog_posts_padding": {
                                    "unit": "px",
                                    "top": "0",
                                    "right": "0",
                                    "bottom": "0",
                                    "left": "0",
                                    "isLinked": false
                                },
                                "ekit_blog_posts_margin": {
                                    "unit": "px",
                                    "top": "0",
                                    "right": "0",
                                    "bottom": "0",
                                    "left": "0",
                                    "isLinked": false
                                },
                                "ekit_blog_posts_text_content_wraper_padding": {
                                    "unit": "px",
                                    "top": "35",
                                    "right": "35",
                                    "bottom": "35",
                                    "left": "35",
                                    "isLinked": true
                                },
                                "ekit_blog_posts_feature_img_radius": {
                                    "unit": "px",
                                    "top": "0",
                                    "right": "0",
                                    "bottom": "0",
                                    "left": "0",
                                    "isLinked": false
                                },
                                "ekit_blog_posts_feature_img_margin": {
                                    "unit": "px",
                                    "top": "0",
                                    "right": "0",
                                    "bottom": "0",
                                    "left": "0",
                                    "isLinked": false
                                },
                                "ekit_blog_posts_feature_img_padding": {
                                    "unit": "px",
                                    "top": "0",
                                    "right": "0",
                                    "bottom": "0",
                                    "left": "0",
                                    "isLinked": false
                                },
                                "ekit_blog_posts_floating_date_typography_group_typography": "custom",
                                "ekit_blog_posts_floating_date_typography_group_font_family": "Sulphur Point",
                                "ekit_blog_posts_floating_date_typography_group_font_size": {
                                    "unit": "px",
                                    "size": 20,
                                    "sizes": []
                                },
                                "ekit_blog_posts_floating_date_typography_group_font_size_tablet": {
                                    "unit": "px",
                                    "size": 17,
                                    "sizes": []
                                },
                                "ekit_blog_posts_floating_date_typography_group_font_size_mobile": {
                                    "unit": "px",
                                    "size": 18,
                                    "sizes": []
                                },
                                "ekit_blog_posts_floating_date_typography_group_font_weight": "700",
                                "ekit_blog_posts_floating_date_typography_group_line_height": {
                                    "unit": "em",
                                    "size": 1.3,
                                    "sizes": []
                                },
                                "ekit_blog_posts_floating_date_typography_group_word_spacing": {
                                    "unit": "em",
                                    "size": "",
                                    "sizes": []
                                },
                                "ekit_blog_posts_floating_date_color": "#FFFFFF",
                                "ekit_blog_posts_floating_date_month_typography_group_typography": "custom",
                                "ekit_blog_posts_floating_date_month_typography_group_font_family": "Sulphur Point",
                                "ekit_blog_posts_floating_date_month_typography_group_font_size": {
                                    "unit": "px",
                                    "size": 13,
                                    "sizes": []
                                },
                                "ekit_blog_posts_floating_date_month_typography_group_font_weight": "bold",
                                "ekit_blog_posts_floating_date_month_typography_group_text_transform": "uppercase",
                                "ekit_blog_posts_floating_date_month_typography_group_line_height": {
                                    "unit": "em",
                                    "size": 1.3,
                                    "sizes": []
                                },
                                "ekit_blog_posts_floating_date_month_typography_group_letter_spacing": {
                                    "unit": "px",
                                    "size": 2,
                                    "sizes": []
                                },
                                "ekit_blog_posts_floating_date_month_color": "#FFFFFFA1",
                                "ekit_blog_posts_floating_date_bg_color_group_background": "classic",
                                "ekit_blog_posts_floating_date_bg_color_group_color": "#121212",
                                "ekit_blog_posts_floating_date_triangle_color": "#DADADA",
                                "ekit_blog_posts_floating_category_typography_typography": "custom",
                                "ekit_blog_posts_floating_category_typography_font_family": "Sulphur Point",
                                "ekit_blog_posts_floating_category_typography_font_size": {
                                    "unit": "px",
                                    "size": 15,
                                    "sizes": []
                                },
                                "ekit_blog_posts_floating_category_typography_font_weight": "400",
                                "ekit_blog_posts_floating_category_typography_line_height": {
                                    "unit": "em",
                                    "size": "",
                                    "sizes": []
                                },
                                "ekit_blog_posts_floating_category_typography_word_spacing": {
                                    "unit": "em",
                                    "size": "",
                                    "sizes": []
                                },
                                "ekit_blog_posts_floating_category_color": "#121212",
                                "ekit_blog_posts_floating_category_bg_color": "#F3F3F3",
                                "ekit_blog_posts_floating_category_padding": {
                                    "unit": "px",
                                    "top": "10",
                                    "right": "15",
                                    "bottom": "10",
                                    "left": "15",
                                    "isLinked": false
                                },
                                "ekit_blog_posts_floating_category_padding_radius": {
                                    "unit": "px",
                                    "top": "0",
                                    "right": "0",
                                    "bottom": "0",
                                    "left": "0",
                                    "isLinked": false
                                },
                                "ekit_blog_posts_title_typography_typography": "custom",
                                "ekit_blog_posts_title_typography_font_family": "Sulphur Point",
                                "ekit_blog_posts_title_typography_font_size": {
                                    "unit": "px",
                                    "size": 25,
                                    "sizes": []
                                },
                                "ekit_blog_posts_title_typography_font_size_tablet": {
                                    "unit": "px",
                                    "size": 23,
                                    "sizes": []
                                },
                                "ekit_blog_posts_title_typography_font_size_mobile": {
                                    "unit": "px",
                                    "size": 20,
                                    "sizes": []
                                },
                                "ekit_blog_posts_title_typography_font_weight": "700",
                                "ekit_blog_posts_title_typography_line_height": {
                                    "unit": "em",
                                    "size": 1.3,
                                    "sizes": []
                                },
                                "ekit_blog_posts_title_typography_word_spacing": {
                                    "unit": "em",
                                    "size": "",
                                    "sizes": []
                                },
                                "ekit_blog_posts_title_color": "#121212",
                                "ekit_blog_posts_title_margin": {
                                    "unit": "px",
                                    "top": "0",
                                    "right": "0",
                                    "bottom": "9",
                                    "left": "0",
                                    "isLinked": false
                                },
                                "ekit_blog_posts_content_color": "#6E6E6E",
                                "ekit_blog_posts_content_typography_typography": "custom",
                                "ekit_blog_posts_content_typography_font_family": "Sulphur Point",
                                "ekit_blog_posts_content_typography_font_size": {
                                    "unit": "px",
                                    "size": 17,
                                    "sizes": []
                                },
                                "ekit_blog_posts_content_typography_font_weight": "400",
                                "ekit_blog_posts_content_typography_text_transform": "none",
                                "ekit_blog_posts_content_typography_line_height": {
                                    "unit": "em",
                                    "size": 1.5,
                                    "sizes": []
                                },
                                "ekit_blog_posts_content_margin": {
                                    "unit": "px",
                                    "top": "0",
                                    "right": "0",
                                    "bottom": "20",
                                    "left": "0",
                                    "isLinked": false
                                },
                                "ekit_blog_posts_btn_text_padding": {
                                    "unit": "px",
                                    "top": "16",
                                    "right": "37",
                                    "bottom": "16",
                                    "left": "37",
                                    "isLinked": false
                                },
                                "ekit_blog_posts_btn_typography_typography": "custom",
                                "ekit_blog_posts_btn_typography_font_family": "Sulphur Point",
                                "ekit_blog_posts_btn_typography_font_size": {
                                    "unit": "px",
                                    "size": 13,
                                    "sizes": []
                                },
                                "ekit_blog_posts_btn_typography_font_weight": "bold",
                                "ekit_blog_posts_btn_typography_text_transform": "uppercase",
                                "ekit_blog_posts_btn_typography_line_height": {
                                    "unit": "em",
                                    "size": 1.3,
                                    "sizes": []
                                },
                                "ekit_blog_posts_btn_typography_letter_spacing": {
                                    "unit": "px",
                                    "size": 2,
                                    "sizes": []
                                },
                                "ekit_blog_posts_btn_bg_color_background": "classic",
                                "ekit_blog_posts_btn_bg_color_color": "#121212",
                                "ekit_blog_posts_btn_hover_color": "#121212",
                                "ekit_blog_posts_btn_bg_hover_color_background": "classic",
                                "ekit_blog_posts_btn_bg_hover_color_color": "#FFFFFF",
                                "ekit_blog_posts_btn_border_radius": {
                                    "unit": "px",
                                    "top": "0",
                                    "right": "0",
                                    "bottom": "0",
                                    "left": "0",
                                    "isLinked": false
                                },
                                "__globals__": {
                                    "ekit_blog_posts_background_color": "globals\/colors?id=4054cab",
                                    "ekit_blog_posts_title_typography_typography": "globals\/typography?id=a10f8a0",
                                    "ekit_blog_posts_title_color": "globals\/colors?id=primary",
                                    "ekit_blog_posts_content_typography_typography": "globals\/typography?id=text",
                                    "ekit_blog_posts_content_color": "globals\/colors?id=text",
                                    "ekit_blog_posts_btn_typography_typography": "globals\/typography?id=accent",
                                    "ekit_blog_posts_btn_bg_color_color": "globals\/colors?id=primary",
                                    "ekit_blog_posts_btn_bg_hover_color_color": "",
                                    "ekit_blog_posts_btn_hover_color": "globals\/colors?id=primary",
                                    "ekit_blog_posts_floating_date_typography_group_typography": "globals\/typography?id=b21c26e",
                                    "ekit_blog_posts_floating_date_month_typography_group_typography": "globals\/typography?id=accent",
                                    "ekit_blog_posts_floating_date_bg_color_group_color": "globals\/colors?id=primary",
                                    "ekit_blog_posts_floating_date_color": "",
                                    "ekit_blog_posts_floating_date_month_color": "globals\/colors?id=fdf12ae",
                                    "ekit_blog_posts_floating_date_triangle_color": "globals\/colors?id=c0dc0f8",
                                    "ekit_blog_posts_floating_category_typography_typography": "globals\/typography?id=1eb2da8",
                                    "ekit_blog_posts_floating_category_bg_color": "globals\/colors?id=secondary",
                                    "ekit_blog_posts_floating_category_color": "globals\/colors?id=primary"
                                }
                            },
                            "elements": [],
                            "isInner": false,
                            "widgetType": "elementskit-blog-posts",
                            "elType": "widget"
                        }
                    ],
                    "isInner": false,
                    "elType": "column"
                }
            ],
            "isInner": false,
            "elType": "section"
        }
    ]
}